{"url":"http://www.cybercom.com/Legal-notice/Website-terms-and-conditions/","runs":3,"browserName":"chrome","browserVersion":"39.0.2171.95","platform":"Mac OS X","userAgent":"Mozilla/5.0 (Macintosh; Intel Mac OS X 10_9_4) AppleWebKit/537.36 (KHTML, like Gecko) Chrome/37.0.2062.120 Safari/537.36","windowSize":"unknown","browserTimeVersion":"0.8.17","statistics":[{"name":"backEndTime","min":"274","max":"836","p10":"274","p70":"836","p80":"836","p90":"836","p99":"836","median":"464","mean":"525"},{"name":"domContentLoadedTime","min":"476","max":"1079","p10":"476","p70":"1079","p80":"1079","p90":"1079","p99":"1079","median":"1071","mean":"875"},{"name":"domInteractiveTime","min":"476","max":"1079","p10":"476","p70":"1079","p80":"1079","p90":"1079","p99":"1079","median":"1071","mean":"875"},{"name":"domainLookupTime","min":"0","max":"0","p10":"0","p70":"0","p80":"0","p90":"0","p99":"0","median":"0","mean":"0"},{"name":"frontEndTime","min":"610","max":"939","p10":"610","p70":"939","p80":"939","p90":"939","p99":"939","median":"747","mean":"765"},{"name":"pageDownloadTime","min":"1","max":"38","p10":"1","p70":"38","p80":"38","p90":"38","p99":"38","median":"2","mean":"14"},{"name":"pageLoadTime","min":"885","max":"1585","p10":"885","p70":"1585","p80":"1585","p90":"1585","p99":"1585","median":"1441","mean":"1304"},{"name":"redirectionTime","min":"184","max":"204","p10":"184","p70":"204","p80":"204","p90":"204","p99":"204","median":"186","mean":"191"},{"name":"serverConnectionTime","min":"0","max":"0","p10":"0","p70":"0","p80":"0","p90":"0","p99":"0","median":"0","mean":"0"},{"name":"serverResponseTime","min":"77","max":"643","p10":"77","p70":"643","p80":"643","p90":"643","p99":"643","median":"286","mean":"335"},{"name":"speedIndex","min":"381","max":"1055","p10":"381","p70":"1055","p80":"1055","p90":"1055","p99":"1055","median":"931","mean":"789"},{"name":"firstPaint","min":"332","max":"1004","p10":"332","p70":"1004","p80":"1004","p90":"1004","p99":"1004","median":"894","mean":"743"}],"data":[{"firstPaint":893.8530000014,"navigation":{"connectEnd":1418678296809,"connectStart":1418678296809,"domComplete":1418678298034,"domContentLoadedEventEnd":1418678297680,"domContentLoadedEventStart":1418678297664,"domInteractive":1418678297664,"domLoading":1418678297060,"domainLookupEnd":1418678296797,"domainLookupStart":1418678296797,"fetchStart":1418678296797,"loadEventEnd":1418678298070,"loadEventStart":1418678298034,"navigationStart":1418678296593,"redirectEnd":0,"redirectStart":0,"requestStart":1418678296809,"responseEnd":1418678297095,"responseStart":1418678297057,"secureConnectionStart":0,"unloadEventEnd":0,"unloadEventStart":0},"resources":[{"connectEnd":469.570000001113,"connectStart":469.070999999531,"domainLookupEnd":468.441999997594,"domainLookupStart":468.441999997594,"duration":425.411000003805,"entryType":"resource","fetchStart":468.441999997594,"initiatorType":"link","name":"http://www.cybercom.com/static/combined_B945C63A6C6B6A4949BBAAD00B579C71.css","redirectEnd":0,"redirectStart":0,"requestStart":469.626999998582,"responseEnd":893.8530000014,"responseStart":855.04100000253,"secureConnectionStart":0,"startTime":468.441999997594},{"connectEnd":469.524999993155,"connectStart":469.156999999541,"domainLookupEnd":468.56399999524,"domainLookupStart":468.56399999524,"duration":404.174000010244,"entryType":"resource","fetchStart":468.56399999524,"initiatorType":"img","name":"http://www.cybercom.com/static/cybercom/img/cybercom_logo.png","redirectEnd":0,"redirectStart":0,"requestStart":469.654999993509,"responseEnd":872.738000005484,"responseStart":857.007999991765,"secureConnectionStart":0,"startTime":468.56399999524},{"connectEnd":480.035000000498,"connectStart":480.035000000498,"domainLookupEnd":480.035000000498,"domainLookupStart":480.035000000498,"duration":598.534999997355,"entryType":"resource","fetchStart":480.035000000498,"initiatorType":"img","name":"http://www.cybercom.com/contentassets/739025bb59e548718adb198ac95c5d7f/helena-borglund110x110.png","redirectEnd":0,"redirectStart":0,"requestStart":873.594000004232,"responseEnd":1078.56999999785,"responseStart":1060.28199999128,"secureConnectionStart":0,"startTime":480.035000000498},{"connectEnd":501.715999998851,"connectStart":501.715999998851,"domainLookupEnd":501.715999998851,"domainLookupStart":501.715999998851,"duration":356.759000002057,"entryType":"resource","fetchStart":501.715999998851,"initiatorType":"script","name":"http://www.cybercom.com/static/cybercom/js/gas-1.10.1.js","redirectEnd":0,"redirectStart":0,"requestStart":503.830999994534,"responseEnd":858.475000000908,"responseStart":856.587000002037,"secureConnectionStart":0,"startTime":501.715999998851},{"connectEnd":503.807000000961,"connectStart":503.016999995452,"domainLookupEnd":501.814000002923,"domainLookupStart":501.814000002923,"duration":417.361999992863,"entryType":"resource","fetchStart":501.814000002923,"initiatorType":"script","name":"http://www.cybercom.com/scripts/combined_C9220CE7B558C8B6CFAD1DA5FEFA214F.js","redirectEnd":0,"redirectStart":0,"requestStart":503.885999991326,"responseEnd":919.175999995787,"responseStart":858.494999993127,"secureConnectionStart":0,"startTime":501.814000002923},{"connectEnd":0,"connectStart":0,"domainLookupEnd":0,"domainLookupStart":0,"duration":85.4370000015479,"entryType":"resource","fetchStart":501.883999997517,"initiatorType":"script","name":"http://s7.addthis.com/js/300/addthis_widget.js","redirectEnd":0,"redirectStart":0,"requestStart":0,"responseEnd":587.320999999065,"responseStart":0,"secureConnectionStart":0,"startTime":501.883999997517},{"connectEnd":0,"connectStart":0,"domainLookupEnd":0,"domainLookupStart":0,"duration":62.5120000040624,"entryType":"resource","fetchStart":501.951999991434,"initiatorType":"script","name":"https://dl.episerver.net/8.10.0/epi-util/native.history.js","redirectEnd":0,"redirectStart":0,"requestStart":0,"responseEnd":564.463999995496,"responseStart":0,"secureConnectionStart":0,"startTime":501.951999991434},{"connectEnd":0,"connectStart":0,"domainLookupEnd":0,"domainLookupStart":0,"duration":59.7459999989951,"entryType":"resource","fetchStart":502.028999995673,"initiatorType":"script","name":"https://dl.episerver.net/8.10.0/epi-util/find.js","redirectEnd":0,"redirectStart":0,"requestStart":0,"responseEnd":561.774999994668,"responseStart":0,"secureConnectionStart":0,"startTime":502.028999995673},{"connectEnd":0,"connectStart":0,"domainLookupEnd":0,"domainLookupStart":0,"duration":74.4459999987157,"entryType":"resource","fetchStart":902.925000002142,"initiatorType":"script","name":"http://www.googletagmanager.com/gtm.js?id=GTM-CVB8","redirectEnd":0,"redirectStart":0,"requestStart":0,"responseEnd":977.371000000858,"responseStart":0,"secureConnectionStart":0,"startTime":902.925000002142},{"connectEnd":0,"connectStart":0,"domainLookupEnd":0,"domainLookupStart":0,"duration":64.3959999870276,"entryType":"resource","fetchStart":906.715000004624,"initiatorType":"script","name":"http://www.google-analytics.com/ga.js","redirectEnd":0,"redirectStart":0,"requestStart":0,"responseEnd":971.110999991652,"responseStart":0,"secureConnectionStart":0,"startTime":906.715000004624},{"connectEnd":909.113999994588,"connectStart":909.113999994588,"domainLookupEnd":909.113999994588,"domainLookupStart":909.113999994588,"duration":173.107000009622,"entryType":"resource","fetchStart":909.113999994588,"initiatorType":"css","name":"http://www.cybercom.com/static/cybercom/img/button-lang.png","redirectEnd":0,"redirectStart":0,"requestStart":911.508000004687,"responseEnd":1082.22100000421,"responseStart":1081.72000000195,"secureConnectionStart":0,"startTime":909.113999994588},{"connectEnd":909.190999998828,"connectStart":909.190999998828,"domainLookupEnd":909.190999998828,"domainLookupStart":909.190999998828,"duration":168.818999998621,"entryType":"resource","fetchStart":909.190999998828,"initiatorType":"css","name":"http://www.cybercom.com/static/cybercom/img/lang-toggle-sprite-small2.png","redirectEnd":0,"redirectStart":0,"requestStart":911.544000002323,"responseEnd":1078.00999999745,"responseStart":1077.20899999549,"secureConnectionStart":0,"startTime":909.190999998828},{"connectEnd":911.527000003844,"connectStart":910.772000002908,"domainLookupEnd":909.3520000024,"domainLookupStart":909.3520000024,"duration":212.883000000147,"entryType":"resource","fetchStart":909.3520000024,"initiatorType":"css","name":"http://www.cybercom.com/static/cybercom/img/button-search.png","redirectEnd":0,"redirectStart":0,"requestStart":911.678999997093,"responseEnd":1122.23500000255,"responseStart":1121.59300000349,"secureConnectionStart":0,"startTime":909.3520000024},{"connectEnd":909.463000003598,"connectStart":909.463000003598,"domainLookupEnd":909.463000003598,"domainLookupStart":909.463000003598,"duration":215.662999995402,"entryType":"resource","fetchStart":909.463000003598,"initiatorType":"css","name":"http://www.cybercom.com/static/cybercom/img/search-toggle-sprite-small.png","redirectEnd":0,"redirectStart":0,"requestStart":919.119999991381,"responseEnd":1125.125999999,"responseStart":1124.38399999519,"secureConnectionStart":0,"startTime":909.463000003598},{"connectEnd":911.598999999114,"connectStart":910.686000002897,"domainLookupEnd":909.998999995878,"domainLookupStart":909.998999995878,"duration":468.131000001449,"entryType":"resource","fetchStart":909.998999995878,"initiatorType":"css","name":"http://www.cybercom.com/static/cybercom/fonts/95e8f876-e592-40be-bed1-3adf4ccb67aa.woff","redirectEnd":0,"redirectStart":0,"requestStart":911.687999992864,"responseEnd":1378.12999999733,"responseStart":1120.49600000319,"secureConnectionStart":0,"startTime":909.998999995878},{"connectEnd":910.812000001897,"connectStart":910.812000001897,"domainLookupEnd":910.812000001897,"domainLookupStart":910.812000001897,"duration":241.597999993246,"entryType":"resource","fetchStart":910.812000001897,"initiatorType":"css","name":"http://www.cybercom.com/static/cybercom/img/footer_x-y.png","redirectEnd":0,"redirectStart":0,"requestStart":1081.24499999394,"responseEnd":1152.40999999514,"responseStart":1151.43099999113,"secureConnectionStart":0,"startTime":910.812000001897},{"connectEnd":911.372000002302,"connectStart":911.372000002302,"domainLookupEnd":911.372000002302,"domainLookupStart":911.372000002302,"duration":240.559999991092,"entryType":"resource","fetchStart":911.372000002302,"initiatorType":"css","name":"http://www.cybercom.com/static/cybercom/img/social-sprite2.png","redirectEnd":0,"redirectStart":0,"requestStart":1079.49400000507,"responseEnd":1151.93199999339,"responseStart":1150.82500000426,"secureConnectionStart":0,"startTime":911.372000002302},{"connectEnd":0,"connectStart":0,"domainLookupEnd":0,"domainLookupStart":0,"duration":312.454999992042,"entryType":"resource","fetchStart":1051.48300000292,"initiatorType":"script","name":"http://ct1.addthis.com/static/r07/core165.js","redirectEnd":0,"redirectStart":0,"requestStart":0,"responseEnd":1363.93799999496,"responseStart":0,"secureConnectionStart":0,"startTime":1051.48300000292},{"connectEnd":0,"connectStart":0,"domainLookupEnd":0,"domainLookupStart":0,"duration":101.481999998214,"entryType":"resource","fetchStart":1103.66999999678,"initiatorType":"script","name":"http://blzsnd02.com/js/33532.js","redirectEnd":0,"redirectStart":0,"requestStart":0,"responseEnd":1205.151999995,"responseStart":0,"secureConnectionStart":0,"startTime":1103.66999999678},{"connectEnd":0,"connectStart":0,"domainLookupEnd":0,"domainLookupStart":0,"duration":31.3190000015311,"entryType":"resource","fetchStart":1123.26599999506,"initiatorType":"img","name":"http://www.google-analytics.com/r/__utm.gif?utmwv=5.6.1&utms=1&utmn=1828568355&utmhn=www.cybercom.com&utmcs=UTF-8&utmsr=1440x900&utmvp=1280x728&utmsc=24-bit&utmul=en-us&utmje=1&utmfl=16.0%20r0&utmdt=Website%20terms%20and%20conditions%20-%20Cybercom&utmhid=1290353956&utmr=-&utmp=%2FLegal-notice%2FWebsite-terms-and-conditions%2F&utmht=1418678297712&utmac=UA-8422471-1&utmgtm=GTM-CVB8&utmcc=__utma%3D194191167.1797066140.1418678298.1418678298.1418678298.1%3B%2B__utmz%3D194191167.1418678298.1.1.utmcsr%3D(direct)%7Cutmccn%3D(direct)%7Cutmcmd%3D(none)%3B&utmjid=1594650786&utmredir=1&utmu=qAAgAABAAAGBAAAAAgAAAQAE~","redirectEnd":0,"redirectStart":0,"requestStart":0,"responseEnd":1154.58499999659,"responseStart":0,"secureConnectionStart":0,"startTime":1123.26599999506},{"connectEnd":0,"connectStart":0,"domainLookupEnd":0,"domainLookupStart":0,"duration":210.009000002174,"entryType":"resource","fetchStart":1154.75699999661,"initiatorType":"script","name":"http://cybercom.disqus.com/count.js","redirectEnd":0,"redirectStart":0,"requestStart":0,"responseEnd":1364.76599999878,"responseStart":0,"secureConnectionStart":0,"startTime":1154.75699999661},{"connectEnd":0,"connectStart":0,"domainLookupEnd":0,"domainLookupStart":0,"duration":40.3669999941485,"entryType":"resource","fetchStart":1397.36499999708,"initiatorType":"link","name":"http://ct1.addthis.com/static/r07/widget/css/widget007.old.css","redirectEnd":0,"redirectStart":0,"requestStart":0,"responseEnd":1437.73199999123,"responseStart":0,"secureConnectionStart":0,"startTime":1397.36499999708},{"connectEnd":0,"connectStart":0,"domainLookupEnd":0,"domainLookupStart":0,"duration":41.6760000080103,"entryType":"resource","fetchStart":1475.53699999116,"initiatorType":"link","name":"http://ct1.addthis.com/static/r07/plugins/counter015.css","redirectEnd":0,"redirectStart":0,"requestStart":0,"responseEnd":1517.21299999917,"responseStart":0,"secureConnectionStart":0,"startTime":1475.53699999116},{"connectEnd":0,"connectStart":0,"domainLookupEnd":0,"domainLookupStart":0,"duration":72.8070000041043,"entryType":"resource","fetchStart":1475.88600000017,"initiatorType":"script","name":"http://ct1.addthis.com/static/r07/plugins/counter020.js","redirectEnd":0,"redirectStart":0,"requestStart":0,"responseEnd":1548.69300000428,"responseStart":0,"secureConnectionStart":0,"startTime":1475.88600000017},{"connectEnd":0,"connectStart":0,"domainLookupEnd":0,"domainLookupStart":0,"duration":109.593000001041,"entryType":"resource","fetchStart":1477.48299999512,"initiatorType":"css","name":"http://ct1.addthis.com/static/r07/widget/img/widget008.old.16.icons.png","redirectEnd":0,"redirectStart":0,"requestStart":0,"responseEnd":1587.07599999616,"responseStart":0,"secureConnectionStart":0,"startTime":1477.48299999512},{"connectEnd":0,"connectStart":0,"domainLookupEnd":0,"domainLookupStart":0,"duration":108.97999998997,"entryType":"resource","fetchStart":1479.16400000395,"initiatorType":"iframe","name":"http://ct1.addthis.com/static/r07/sh180.html","redirectEnd":0,"redirectStart":0,"requestStart":0,"responseEnd":1588.14399999392,"responseStart":0,"secureConnectionStart":0,"startTime":1479.16400000395},{"connectEnd":0,"connectStart":0,"domainLookupEnd":0,"domainLookupStart":0,"duration":77.607999992324,"entryType":"resource","fetchStart":1580.43800000451,"initiatorType":"script","name":"http://api-public.addthis.com/url/shares.json?url=http%3A%2F%2Fwww.cybercom.com%2FLegal-notice%2FWebsite-terms-and-conditions%2F&callback=_ate.cbs.sc_httpwwwcybercomcomlegalnoticewebsitetermsandconditions0","redirectEnd":0,"redirectStart":0,"requestStart":0,"responseEnd":1658.04599999683,"responseStart":0,"secureConnectionStart":0,"startTime":1580.43800000451}],"speedIndex":930.778900554005,"timings":{"backEndTime":464,"domContentLoadedTime":1071,"domInteractiveTime":1071,"domainLookupTime":0,"frontEndTime":939,"pageDownloadTime":38,"pageLoadTime":1441,"redirectionTime":204,"serverConnectionTime":0,"serverResponseTime":286},"userTiming":{"marks":[],"measures":[]}},{"firstPaint":1004.40200000594,"navigation":{"connectEnd":1418678299678,"connectStart":1418678299677,"domComplete":1418678301068,"domContentLoadedEventEnd":1418678300635,"domContentLoadedEventStart":1418678300562,"domInteractive":1418678300562,"domLoading":1418678300322,"domainLookupEnd":1418678299667,"domainLookupStart":1418678299667,"fetchStart":1418678299667,"loadEventEnd":1418678301105,"loadEventStart":1418678301068,"navigationStart":1418678299483,"redirectEnd":0,"redirectStart":0,"requestStart":1418678299678,"responseEnd":1418678300321,"responseStart":1418678300319,"secureConnectionStart":0,"unloadEventEnd":0,"unloadEventStart":0},"resources":[{"connectEnd":842.008000006899,"connectStart":842.008000006899,"domainLookupEnd":842.008000006899,"domainLookupStart":842.008000006899,"duration":162.39399999904,"entryType":"resource","fetchStart":842.008000006899,"initiatorType":"link","name":"http://www.cybercom.com/static/combined_B945C63A6C6B6A4949BBAAD00B579C71.css","redirectEnd":0,"redirectStart":0,"requestStart":844.519000005676,"responseEnd":1004.40200000594,"responseStart":1001.46400000085,"secureConnectionStart":0,"startTime":842.008000006899},{"connectEnd":844.540000005509,"connectStart":843.402000013157,"domainLookupEnd":842.144000009284,"domainLookupStart":842.144000009284,"duration":161.022999993293,"entryType":"resource","fetchStart":842.144000009284,"initiatorType":"img","name":"http://www.cybercom.com/static/cybercom/img/cybercom_logo.png","redirectEnd":0,"redirectStart":0,"requestStart":844.670000005863,"responseEnd":1003.16700000258,"responseStart":1001.90400000429,"secureConnectionStart":0,"startTime":842.144000009284},{"connectEnd":842.20000001369,"connectStart":842.20000001369,"domainLookupEnd":842.20000001369,"domainLookupStart":842.20000001369,"duration":200.478999991901,"entryType":"resource","fetchStart":842.20000001369,"initiatorType":"img","name":"http://www.cybercom.com/contentassets/739025bb59e548718adb198ac95c5d7f/helena-borglund110x110.png","redirectEnd":0,"redirectStart":0,"requestStart":1004.13100000878,"responseEnd":1042.67900000559,"responseStart":1041.95900000923,"secureConnectionStart":0,"startTime":842.20000001369},{"connectEnd":844.467000002624,"connectStart":843.493000007584,"domainLookupEnd":842.270000008284,"domainLookupStart":842.270000008284,"duration":157.458000001498,"entryType":"resource","fetchStart":842.270000008284,"initiatorType":"script","name":"http://www.cybercom.com/static/cybercom/js/gas-1.10.1.js","redirectEnd":0,"redirectStart":0,"requestStart":844.542000006186,"responseEnd":999.728000009782,"responseStart":998.868000009679,"secureConnectionStart":0,"startTime":842.270000008284},{"connectEnd":844.458000006853,"connectStart":843.691000001854,"domainLookupEnd":842.32900000643,"domainLookupStart":842.32900000643,"duration":155.513000005158,"entryType":"resource","fetchStart":842.32900000643,"initiatorType":"script","name":"http://www.cybercom.com/scripts/combined_C9220CE7B558C8B6CFAD1DA5FEFA214F.js","redirectEnd":0,"redirectStart":0,"requestStart":844.561000005342,"responseEnd":997.842000011588,"responseStart":995.441000006395,"secureConnectionStart":0,"startTime":842.32900000643},{"connectEnd":0,"connectStart":0,"domainLookupEnd":0,"domainLookupStart":0,"duration":58.4930000040913,"entryType":"resource","fetchStart":842.388000004576,"initiatorType":"script","name":"http://s7.addthis.com/js/300/addthis_widget.js","redirectEnd":0,"redirectStart":0,"requestStart":0,"responseEnd":900.881000008667,"responseStart":0,"secureConnectionStart":0,"startTime":842.388000004576},{"connectEnd":0,"connectStart":0,"domainLookupEnd":0,"domainLookupStart":0,"duration":56.7449999944074,"entryType":"resource","fetchStart":842.45200001169,"initiatorType":"script","name":"https://dl.episerver.net/8.10.0/epi-util/native.history.js","redirectEnd":0,"redirectStart":0,"requestStart":0,"responseEnd":899.197000006097,"responseStart":0,"secureConnectionStart":0,"startTime":842.45200001169},{"connectEnd":0,"connectStart":0,"domainLookupEnd":0,"domainLookupStart":0,"duration":54.5140000031097,"entryType":"resource","fetchStart":842.505000007805,"initiatorType":"script","name":"https://dl.episerver.net/8.10.0/epi-util/find.js","redirectEnd":0,"redirectStart":0,"requestStart":0,"responseEnd":897.019000010914,"responseStart":0,"secureConnectionStart":0,"startTime":842.505000007805},{"connectEnd":0,"connectStart":0,"domainLookupEnd":0,"domainLookupStart":0,"duration":32.6740000018617,"entryType":"resource","fetchStart":1014.46800000849,"initiatorType":"script","name":"http://www.googletagmanager.com/gtm.js?id=GTM-CVB8","redirectEnd":0,"redirectStart":0,"requestStart":0,"responseEnd":1047.14200001035,"responseStart":0,"secureConnectionStart":0,"startTime":1014.46800000849},{"connectEnd":0,"connectStart":0,"domainLookupEnd":0,"domainLookupStart":0,"duration":20.6369999941671,"entryType":"resource","fetchStart":1019.93000000948,"initiatorType":"script","name":"http://www.google-analytics.com/ga.js","redirectEnd":0,"redirectStart":0,"requestStart":0,"responseEnd":1040.56700000365,"responseStart":0,"secureConnectionStart":0,"startTime":1019.93000000948},{"connectEnd":0,"connectStart":0,"domainLookupEnd":0,"domainLookupStart":0,"duration":289.210999995703,"entryType":"resource","fetchStart":1069.16500000807,"initiatorType":"script","name":"http://ct1.addthis.com/static/r07/core165.js","redirectEnd":0,"redirectStart":0,"requestStart":0,"responseEnd":1358.37600000377,"responseStart":0,"secureConnectionStart":0,"startTime":1069.16500000807},{"connectEnd":1082.21100000083,"connectStart":1082.21100000083,"domainLookupEnd":1082.21100000083,"domainLookupStart":1082.21100000083,"duration":274.927000005846,"entryType":"resource","fetchStart":1082.21100000083,"initiatorType":"css","name":"http://www.cybercom.com/static/cybercom/img/button-lang.png","redirectEnd":0,"redirectStart":0,"requestStart":1083.42400001129,"responseEnd":1357.13800000667,"responseStart":1356.42800001369,"secureConnectionStart":0,"startTime":1082.21100000083},{"connectEnd":1082.30100000219,"connectStart":1082.30100000219,"domainLookupEnd":1082.30100000219,"domainLookupStart":1082.30100000219,"duration":271.954000010737,"entryType":"resource","fetchStart":1082.30100000219,"initiatorType":"css","name":"http://www.cybercom.com/static/cybercom/img/lang-toggle-sprite-small2.png","redirectEnd":0,"redirectStart":0,"requestStart":1083.42300000368,"responseEnd":1354.25500001293,"responseStart":1353.78500001389,"secureConnectionStart":0,"startTime":1082.30100000219},{"connectEnd":1082.46700000018,"connectStart":1082.46700000018,"domainLookupEnd":1082.46700000018,"domainLookupStart":1082.46700000018,"duration":276.611000008415,"entryType":"resource","fetchStart":1082.46700000018,"initiatorType":"css","name":"http://www.cybercom.com/static/cybercom/img/button-search.png","redirectEnd":0,"redirectStart":0,"requestStart":1083.47400001367,"responseEnd":1359.07800000859,"responseStart":1358.37500001071,"secureConnectionStart":0,"startTime":1082.46700000018},{"connectEnd":1082.5760000007,"connectStart":1082.5760000007,"domainLookupEnd":1082.5760000007,"domainLookupStart":1082.5760000007,"duration":270.046000005095,"entryType":"resource","fetchStart":1082.5760000007,"initiatorType":"css","name":"http://www.cybercom.com/static/cybercom/img/search-toggle-sprite-small.png","redirectEnd":0,"redirectStart":0,"requestStart":1083.53900001384,"responseEnd":1352.62200000579,"responseStart":1351.76900000079,"secureConnectionStart":0,"startTime":1082.5760000007},{"connectEnd":1084.41100000346,"connectStart":1083.69600000151,"domainLookupEnd":1083.06700001413,"domainLookupStart":1083.06700001413,"duration":262.738999997964,"entryType":"resource","fetchStart":1083.06700001413,"initiatorType":"css","name":"http://www.cybercom.com/static/cybercom/fonts/95e8f876-e592-40be-bed1-3adf4ccb67aa.woff","redirectEnd":0,"redirectStart":0,"requestStart":1084.44900000177,"responseEnd":1345.80600001209,"responseStart":1344.46700000262,"secureConnectionStart":0,"startTime":1083.06700001413},{"connectEnd":1084.52500001295,"connectStart":1084.19000000868,"domainLookupEnd":1083.70700001251,"domainLookupStart":1083.70700001251,"duration":264.581999988877,"entryType":"resource","fetchStart":1083.70700001251,"initiatorType":"css","name":"http://www.cybercom.com/static/cybercom/img/footer_x-y.png","redirectEnd":0,"redirectStart":0,"requestStart":1084.58200001041,"responseEnd":1348.28900000139,"responseStart":1347.53700000874,"secureConnectionStart":0,"startTime":1083.70700001251},{"connectEnd":1084.1700000019,"connectStart":1084.1700000019,"domainLookupEnd":1084.1700000019,"domainLookupStart":1084.1700000019,"duration":500.719000003301,"entryType":"resource","fetchStart":1084.1700000019,"initiatorType":"css","name":"http://www.cybercom.com/static/cybercom/img/social-sprite2.png","redirectEnd":0,"redirectStart":0,"requestStart":1346.62500000559,"responseEnd":1584.88900000521,"responseStart":1583.59000000928,"secureConnectionStart":0,"startTime":1084.1700000019},{"connectEnd":0,"connectStart":0,"domainLookupEnd":0,"domainLookupStart":0,"duration":181.019000010565,"entryType":"resource","fetchStart":1158.42300000077,"initiatorType":"script","name":"http://cybercom.disqus.com/count.js","redirectEnd":0,"redirectStart":0,"requestStart":0,"responseEnd":1339.44200001133,"responseStart":0,"secureConnectionStart":0,"startTime":1158.42300000077},{"connectEnd":0,"connectStart":0,"domainLookupEnd":0,"domainLookupStart":0,"duration":219.349999999395,"entryType":"resource","fetchStart":1172.63600000297,"initiatorType":"script","name":"http://blzsnd02.com/js/33532.js","redirectEnd":0,"redirectStart":0,"requestStart":0,"responseEnd":1391.98600000236,"responseStart":0,"secureConnectionStart":0,"startTime":1172.63600000297},{"connectEnd":0,"connectStart":0,"domainLookupEnd":0,"domainLookupStart":0,"duration":181.252999987919,"entryType":"resource","fetchStart":1189.51400001242,"initiatorType":"img","name":"http://www.google-analytics.com/r/__utm.gif?utmwv=5.6.1&utms=1&utmn=619714729&utmhn=www.cybercom.com&utmcs=UTF-8&utmsr=1440x900&utmvp=1280x728&utmsc=24-bit&utmul=en-us&utmje=1&utmfl=16.0%20r0&utmdt=Website%20terms%20and%20conditions%20-%20Cybercom&utmhid=1316886036&utmr=-&utmp=%2FLegal-notice%2FWebsite-terms-and-conditions%2F&utmht=1418678300669&utmac=UA-8422471-1&utmgtm=GTM-CVB8&utmcc=__utma%3D194191167.248056956.1418678301.1418678301.1418678301.1%3B%2B__utmz%3D194191167.1418678301.1.1.utmcsr%3D(direct)%7Cutmccn%3D(direct)%7Cutmcmd%3D(none)%3B&utmjid=830317549&utmredir=1&utmu=qAAgAABAAAGBAAAAAgAAAQAE~","redirectEnd":0,"redirectStart":0,"requestStart":0,"responseEnd":1370.76700000034,"responseStart":0,"secureConnectionStart":0,"startTime":1189.51400001242},{"connectEnd":0,"connectStart":0,"domainLookupEnd":0,"domainLookupStart":0,"duration":44.4090000091819,"entryType":"resource","fetchStart":1400.46200000506,"initiatorType":"link","name":"http://ct1.addthis.com/static/r07/widget/css/widget007.old.css","redirectEnd":0,"redirectStart":0,"requestStart":0,"responseEnd":1444.87100001425,"responseStart":0,"secureConnectionStart":0,"startTime":1400.46200000506},{"connectEnd":0,"connectStart":0,"domainLookupEnd":0,"domainLookupStart":0,"duration":228.610999998637,"entryType":"resource","fetchStart":1621.61500001093,"initiatorType":"link","name":"http://ct1.addthis.com/static/r07/plugins/counter015.css","redirectEnd":0,"redirectStart":0,"requestStart":0,"responseEnd":1850.22600000957,"responseStart":0,"secureConnectionStart":0,"startTime":1621.61500001093},{"connectEnd":0,"connectStart":0,"domainLookupEnd":0,"domainLookupStart":0,"duration":42.1889999997802,"entryType":"resource","fetchStart":1621.9390000042,"initiatorType":"script","name":"http://ct1.addthis.com/static/r07/plugins/counter020.js","redirectEnd":0,"redirectStart":0,"requestStart":0,"responseEnd":1664.12800000398,"responseStart":0,"secureConnectionStart":0,"startTime":1621.9390000042},{"connectEnd":0,"connectStart":0,"domainLookupEnd":0,"domainLookupStart":0,"duration":233.292999997502,"entryType":"resource","fetchStart":1622.84300000465,"initiatorType":"css","name":"http://ct1.addthis.com/static/r07/widget/img/widget008.old.16.icons.png","redirectEnd":0,"redirectStart":0,"requestStart":0,"responseEnd":1856.13600000215,"responseStart":0,"secureConnectionStart":0,"startTime":1622.84300000465},{"connectEnd":0,"connectStart":0,"domainLookupEnd":0,"domainLookupStart":0,"duration":219.013000008999,"entryType":"resource","fetchStart":1623.7770000007,"initiatorType":"iframe","name":"http://ct1.addthis.com/static/r07/sh180.html","redirectEnd":0,"redirectStart":0,"requestStart":0,"responseEnd":1842.7900000097,"responseStart":0,"secureConnectionStart":0,"startTime":1623.7770000007},{"connectEnd":0,"connectStart":0,"domainLookupEnd":0,"domainLookupStart":0,"duration":189.6310000011,"entryType":"resource","fetchStart":1695.96000001184,"initiatorType":"script","name":"http://api-public.addthis.com/url/shares.json?url=http%3A%2F%2Fwww.cybercom.com%2FLegal-notice%2FWebsite-terms-and-conditions%2F&callback=_ate.cbs.sc_httpwwwcybercomcomlegalnoticewebsitetermsandconditions0","redirectEnd":0,"redirectStart":0,"requestStart":0,"responseEnd":1885.59100001294,"responseStart":0,"secureConnectionStart":0,"startTime":1695.96000001184}],"speedIndex":1055.05791268294,"timings":{"backEndTime":836,"domContentLoadedTime":1079,"domInteractiveTime":1079,"domainLookupTime":0,"frontEndTime":747,"pageDownloadTime":2,"pageLoadTime":1585,"redirectionTime":184,"serverConnectionTime":0,"serverResponseTime":643},"userTiming":{"marks":[],"measures":[]}},{"firstPaint":331.848000001628,"navigation":{"connectEnd":1418678302877,"connectStart":1418678302876,"domComplete":1418678303564,"domContentLoadedEventEnd":1418678303165,"domContentLoadedEventStart":1418678303155,"domInteractive":1418678303155,"domLoading":1418678302956,"domainLookupEnd":1418678302865,"domainLookupStart":1418678302865,"fetchStart":1418678302865,"loadEventEnd":1418678303602,"loadEventStart":1418678303564,"navigationStart":1418678302679,"redirectEnd":0,"redirectStart":0,"requestStart":1418678302877,"responseEnd":1418678302954,"responseStart":1418678302953,"secureConnectionStart":0,"unloadEventEnd":0,"unloadEventStart":0},"resources":[{"connectEnd":279.448000001139,"connectStart":279.448000001139,"domainLookupEnd":279.448000001139,"domainLookupStart":279.448000001139,"duration":52.4000000004889,"entryType":"resource","fetchStart":279.448000001139,"initiatorType":"link","name":"http://www.cybercom.com/static/combined_B945C63A6C6B6A4949BBAAD00B579C71.css","redirectEnd":0,"redirectStart":0,"requestStart":282.089000000269,"responseEnd":331.848000001628,"responseStart":317.901000002166,"secureConnectionStart":0,"startTime":279.448000001139},{"connectEnd":282.092000008561,"connectStart":280.934000009438,"domainLookupEnd":279.584999996587,"domainLookupStart":279.584999996587,"duration":41.8500000087079,"entryType":"resource","fetchStart":279.584999996587,"initiatorType":"img","name":"http://www.cybercom.com/static/cybercom/img/cybercom_logo.png","redirectEnd":0,"redirectStart":0,"requestStart":282.229000004008,"responseEnd":321.435000005295,"responseStart":320.166000004974,"secureConnectionStart":0,"startTime":279.584999996587},{"connectEnd":279.64599999541,"connectStart":279.64599999541,"domainLookupEnd":279.64599999541,"domainLookupStart":279.64599999541,"duration":76.4190000045346,"entryType":"resource","fetchStart":279.64599999541,"initiatorType":"img","name":"http://www.cybercom.com/contentassets/739025bb59e548718adb198ac95c5d7f/helena-borglund110x110.png","redirectEnd":0,"redirectStart":0,"requestStart":321.974999998929,"responseEnd":356.064999999944,"responseStart":354.390000007697,"secureConnectionStart":0,"startTime":279.64599999541},{"connectEnd":282.051999995019,"connectStart":281.0610000015,"domainLookupEnd":279.739999998128,"domainLookupStart":279.739999998128,"duration":38.0140000052052,"entryType":"resource","fetchStart":279.739999998128,"initiatorType":"script","name":"http://www.cybercom.com/static/cybercom/js/gas-1.10.1.js","redirectEnd":0,"redirectStart":0,"requestStart":282.12099999655,"responseEnd":317.754000003333,"responseStart":316.254000004847,"secureConnectionStart":0,"startTime":279.739999998128},{"connectEnd":282.030000002123,"connectStart":281.266999998479,"domainLookupEnd":279.798999996274,"domainLookupStart":279.798999996274,"duration":36.4939999999478,"entryType":"resource","fetchStart":279.798999996274,"initiatorType":"script","name":"http://www.cybercom.com/scripts/combined_C9220CE7B558C8B6CFAD1DA5FEFA214F.js","redirectEnd":0,"redirectStart":0,"requestStart":282.130999999936,"responseEnd":316.292999996222,"responseStart":313.41099999554,"secureConnectionStart":0,"startTime":279.798999996274},{"connectEnd":0,"connectStart":0,"domainLookupEnd":0,"domainLookupStart":0,"duration":46.875,"entryType":"resource","fetchStart":279.859999995097,"initiatorType":"script","name":"http://s7.addthis.com/js/300/addthis_widget.js","redirectEnd":0,"redirectStart":0,"requestStart":0,"responseEnd":326.734999995097,"responseStart":0,"secureConnectionStart":0,"startTime":279.859999995097},{"connectEnd":0,"connectStart":0,"domainLookupEnd":0,"domainLookupStart":0,"duration":66.3260000001174,"entryType":"resource","fetchStart":279.982000007294,"initiatorType":"script","name":"https://dl.episerver.net/8.10.0/epi-util/native.history.js","redirectEnd":0,"redirectStart":0,"requestStart":0,"responseEnd":346.308000007411,"responseStart":0,"secureConnectionStart":0,"startTime":279.982000007294},{"connectEnd":0,"connectStart":0,"domainLookupEnd":0,"domainLookupStart":0,"duration":65.1829999987967,"entryType":"resource","fetchStart":280.041999998502,"initiatorType":"script","name":"https://dl.episerver.net/8.10.0/epi-util/find.js","redirectEnd":0,"redirectStart":0,"requestStart":0,"responseEnd":345.224999997299,"responseStart":0,"secureConnectionStart":0,"startTime":280.041999998502},{"connectEnd":0,"connectStart":0,"domainLookupEnd":0,"domainLookupStart":0,"duration":33.3230000105687,"entryType":"resource","fetchStart":343.015999998897,"initiatorType":"script","name":"http://www.googletagmanager.com/gtm.js?id=GTM-CVB8","redirectEnd":0,"redirectStart":0,"requestStart":0,"responseEnd":376.339000009466,"responseStart":0,"secureConnectionStart":0,"startTime":343.015999998897},{"connectEnd":0,"connectStart":0,"domainLookupEnd":0,"domainLookupStart":0,"duration":23.5800000082236,"entryType":"resource","fetchStart":347.23899999517,"initiatorType":"script","name":"http://www.google-analytics.com/ga.js","redirectEnd":0,"redirectStart":0,"requestStart":0,"responseEnd":370.819000003394,"responseStart":0,"secureConnectionStart":0,"startTime":347.23899999517},{"connectEnd":0,"connectStart":0,"domainLookupEnd":0,"domainLookupStart":0,"duration":326.654000004055,"entryType":"resource","fetchStart":394.272999998066,"initiatorType":"script","name":"http://ct1.addthis.com/static/r07/core165.js","redirectEnd":0,"redirectStart":0,"requestStart":0,"responseEnd":720.927000002121,"responseStart":0,"secureConnectionStart":0,"startTime":394.272999998066},{"connectEnd":394.992000001366,"connectStart":394.992000001366,"domainLookupEnd":394.992000001366,"domainLookupStart":394.992000001366,"duration":319.692000004579,"entryType":"resource","fetchStart":394.992000001366,"initiatorType":"css","name":"http://www.cybercom.com/static/cybercom/img/footer_x-y.png","redirectEnd":0,"redirectStart":0,"requestStart":396.625000008498,"responseEnd":714.684000005946,"responseStart":712.907000008272,"secureConnectionStart":0,"startTime":394.992000001366},{"connectEnd":395.101000001887,"connectStart":395.101000001887,"domainLookupEnd":395.101000001887,"domainLookupStart":395.101000001887,"duration":326.629000002868,"entryType":"resource","fetchStart":395.101000001887,"initiatorType":"css","name":"http://www.cybercom.com/static/cybercom/fonts/95e8f876-e592-40be-bed1-3adf4ccb67aa.woff","redirectEnd":0,"redirectStart":0,"requestStart":396.644000007655,"responseEnd":721.730000004754,"responseStart":719.702000002144,"secureConnectionStart":0,"startTime":395.101000001887},{"connectEnd":395.528000008198,"connectStart":395.528000008198,"domainLookupEnd":395.528000008198,"domainLookupStart":395.528000008198,"duration":319.324999989476,"entryType":"resource","fetchStart":395.528000008198,"initiatorType":"css","name":"http://www.cybercom.com/static/cybercom/img/social-sprite2.png","redirectEnd":0,"redirectStart":0,"requestStart":396.924000000581,"responseEnd":714.852999997675,"responseStart":713.543999998365,"secureConnectionStart":0,"startTime":395.528000008198},{"connectEnd":395.801000006031,"connectStart":395.801000006031,"domainLookupEnd":395.801000006031,"domainLookupStart":395.801000006031,"duration":314.077999995789,"entryType":"resource","fetchStart":395.801000006031,"initiatorType":"css","name":"http://www.cybercom.com/static/cybercom/img/button-lang.png","redirectEnd":0,"redirectStart":0,"requestStart":397.458000006736,"responseEnd":709.87900000182,"responseStart":709.178000004613,"secureConnectionStart":0,"startTime":395.801000006031},{"connectEnd":397.461000000476,"connectStart":396.936000004644,"domainLookupEnd":395.868999999948,"domainLookupStart":395.868999999948,"duration":326.016999999411,"entryType":"resource","fetchStart":395.868999999948,"initiatorType":"css","name":"http://www.cybercom.com/static/cybercom/img/lang-toggle-sprite-small2.png","redirectEnd":0,"redirectStart":0,"requestStart":397.635000001173,"responseEnd":721.885999999358,"responseStart":721.038999996381,"secureConnectionStart":0,"startTime":395.868999999948},{"connectEnd":397.553000002517,"connectStart":397.217000005185,"domainLookupEnd":396.026000002166,"domainLookupStart":396.026000002166,"duration":319.029000005685,"entryType":"resource","fetchStart":396.026000002166,"initiatorType":"css","name":"http://www.cybercom.com/static/cybercom/img/button-search.png","redirectEnd":0,"redirectStart":0,"requestStart":397.718000007444,"responseEnd":715.055000007851,"responseStart":713.885000004666,"secureConnectionStart":0,"startTime":396.026000002166},{"connectEnd":396.126999999979,"connectStart":396.126999999979,"domainLookupEnd":396.126999999979,"domainLookupStart":396.126999999979,"duration":343.15100000822,"entryType":"resource","fetchStart":396.126999999979,"initiatorType":"css","name":"http://www.cybercom.com/static/cybercom/img/search-toggle-sprite-small.png","redirectEnd":0,"redirectStart":0,"requestStart":710.269999995944,"responseEnd":739.278000008198,"responseStart":738.049000006868,"secureConnectionStart":0,"startTime":396.126999999979},{"connectEnd":0,"connectStart":0,"domainLookupEnd":0,"domainLookupStart":0,"duration":250.889000002644,"entryType":"resource","fetchStart":504.784999997355,"initiatorType":"script","name":"http://blzsnd02.com/js/33532.js","redirectEnd":0,"redirectStart":0,"requestStart":0,"responseEnd":755.673999999999,"responseStart":0,"secureConnectionStart":0,"startTime":504.784999997355},{"connectEnd":0,"connectStart":0,"domainLookupEnd":0,"domainLookupStart":0,"duration":206.472000005306,"entryType":"resource","fetchStart":522.016000002623,"initiatorType":"img","name":"http://www.google-analytics.com/r/__utm.gif?utmwv=5.6.1&utms=1&utmn=86347940&utmhn=www.cybercom.com&utmcs=UTF-8&utmsr=1440x900&utmvp=1280x728&utmsc=24-bit&utmul=en-us&utmje=1&utmfl=16.0%20r0&utmdt=Website%20terms%20and%20conditions%20-%20Cybercom&utmhid=1191120648&utmr=-&utmp=%2FLegal-notice%2FWebsite-terms-and-conditions%2F&utmht=1418678303197&utmac=UA-8422471-1&utmgtm=GTM-CVB8&utmcc=__utma%3D194191167.261363471.1418678303.1418678303.1418678303.1%3B%2B__utmz%3D194191167.1418678303.1.1.utmcsr%3D(direct)%7Cutmccn%3D(direct)%7Cutmcmd%3D(none)%3B&utmjid=563757505&utmredir=1&utmu=qAAgAABAAAGBAAAAAgAAAQAE~","redirectEnd":0,"redirectStart":0,"requestStart":0,"responseEnd":728.488000007928,"responseStart":0,"secureConnectionStart":0,"startTime":522.016000002623},{"connectEnd":0,"connectStart":0,"domainLookupEnd":0,"domainLookupStart":0,"duration":37.6239999895915,"entryType":"resource","fetchStart":705.014000006486,"initiatorType":"script","name":"http://cybercom.disqus.com/count.js","redirectEnd":0,"redirectStart":0,"requestStart":0,"responseEnd":742.637999996077,"responseStart":0,"secureConnectionStart":0,"startTime":705.014000006486},{"connectEnd":0,"connectStart":0,"domainLookupEnd":0,"domainLookupStart":0,"duration":41.7950000119163,"entryType":"resource","fetchStart":755.663999996614,"initiatorType":"link","name":"http://ct1.addthis.com/static/r07/widget/css/widget007.old.css","redirectEnd":0,"redirectStart":0,"requestStart":0,"responseEnd":797.45900000853,"responseStart":0,"secureConnectionStart":0,"startTime":755.663999996614},{"connectEnd":0,"connectStart":0,"domainLookupEnd":0,"domainLookupStart":0,"duration":297.952000008081,"entryType":"resource","fetchStart":921.463999999105,"initiatorType":"link","name":"http://ct1.addthis.com/static/r07/plugins/counter015.css","redirectEnd":0,"redirectStart":0,"requestStart":0,"responseEnd":1219.41600000719,"responseStart":0,"secureConnectionStart":0,"startTime":921.463999999105},{"connectEnd":0,"connectStart":0,"domainLookupEnd":0,"domainLookupStart":0,"duration":39.3119999935152,"entryType":"resource","fetchStart":922.009000001708,"initiatorType":"script","name":"http://ct1.addthis.com/static/r07/plugins/counter020.js","redirectEnd":0,"redirectStart":0,"requestStart":0,"responseEnd":961.320999995223,"responseStart":0,"secureConnectionStart":0,"startTime":922.009000001708},{"connectEnd":0,"connectStart":0,"domainLookupEnd":0,"domainLookupStart":0,"duration":284.640999991098,"entryType":"resource","fetchStart":923.372000004747,"initiatorType":"css","name":"http://ct1.addthis.com/static/r07/widget/img/widget008.old.16.icons.png","redirectEnd":0,"redirectStart":0,"requestStart":0,"responseEnd":1208.01299999584,"responseStart":0,"secureConnectionStart":0,"startTime":923.372000004747},{"connectEnd":0,"connectStart":0,"domainLookupEnd":0,"domainLookupStart":0,"duration":284.264999994775,"entryType":"resource","fetchStart":924.507000003359,"initiatorType":"iframe","name":"http://ct1.addthis.com/static/r07/sh180.html","redirectEnd":0,"redirectStart":0,"requestStart":0,"responseEnd":1208.77199999813,"responseStart":0,"secureConnectionStart":0,"startTime":924.507000003359},{"connectEnd":0,"connectStart":0,"domainLookupEnd":0,"domainLookupStart":0,"duration":247.427000009338,"entryType":"resource","fetchStart":996.096999995643,"initiatorType":"script","name":"http://api-public.addthis.com/url/shares.json?url=http%3A%2F%2Fwww.cybercom.com%2FLegal-notice%2FWebsite-terms-and-conditions%2F&callback=_ate.cbs.sc_httpwwwcybercomcomlegalnoticewebsitetermsandconditions0","redirectEnd":0,"redirectStart":0,"requestStart":0,"responseEnd":1243.52400000498,"responseStart":0,"secureConnectionStart":0,"startTime":996.096999995643}],"speedIndex":381.301510378109,"timings":{"backEndTime":274,"domContentLoadedTime":476,"domInteractiveTime":476,"domainLookupTime":0,"frontEndTime":610,"pageDownloadTime":1,"pageLoadTime":885,"redirectionTime":186,"serverConnectionTime":0,"serverResponseTime":77},"userTiming":{"marks":[],"measures":[]}}]}